cosmos/__init__.py
cosmos/adapt_grid/grid/__init__.py
cosmos/adapt_grid/grid/grid.py
cosmos/adapt_grid/grid/grid_margin.py
cosmos/adapt_grid/grid/margin_summary.py
cosmos/dms_data/__init__.py
cosmos/dms_data/dms_data.py
cosmos/dms_data/plot.py
cosmos/hgvs.py
cosmos/likelihood/__init__.py
cosmos/likelihood/double/__init__.py
cosmos/likelihood/double/double.py
cosmos/likelihood/likelihood.py
cosmos/model_analyzer/__init__.py
cosmos/model_analyzer/model_analyzer.py
cosmos/model_analyzer/plot.py
cosmos/model_builder/__init__.py
cosmos/model_builder/model_builder.py
cosmos/model_builder/model_loglik.py
cosmos/model_comparator/__init__.py
cosmos/model_comparator/elpd_pairwise.py
cosmos/plot.py
cosmos/prior_factory/__init__.py
cosmos/prior_factory/plot.py
cosmos/prior_factory/prior_factory.py
cosmos/prior_factory/prior_generator.py
cosmos/simulator/__init__.py
cosmos/simulator/sim_config.py
cosmos/simulator/simulator.py
cosmos_dms-1.0.2.dist-info/LICENSE
cosmos_dms-1.0.2.dist-info/METADATA
cosmos_dms-1.0.2.dist-info/WHEEL
cosmos_dms-1.0.2.dist-info/RECORD
