Metadata-Version: 2.3
Name: cosmos-dms
Version: 1.0.2
Summary: Cosmos: A Position-Resolution Causal Model for Direct and Indirect Effects in Protein Functions
License: MIT
Author: Jingyou Rao
Author-email: roseraosh@gmail.com
Requires-Python: >=3.12
Classifier: License :: OSI Approved :: MIT License
Classifier: Programming Language :: Python :: 3
Classifier: Programming Language :: Python :: 3.12
Classifier: Programming Language :: Python :: 3.13
Requires-Dist: adjustText
Requires-Dist: arviz (>=0.20,<0.21)
Requires-Dist: matplotlib (>=3.9)
Requires-Dist: numpy (>=2.1,<3.0)
Requires-Dist: pandas (>=2.2,<3.0)
Requires-Dist: scikit-learn (>=1.4,<2.0)
Requires-Dist: scipy (>=1.14,<2.0)
Requires-Dist: seaborn (>=0.13)
Requires-Dist: xarray (>=2024.09,<2025.0)
